traceroute/__init__.py
traceroute/__version__.py
traceroute/_data.py
traceroute/_traceroute.py
traceroute/_tracert.py
traceroute-19.2.0.dist-info/LICENSE
traceroute-19.2.0.dist-info/METADATA
traceroute-19.2.0.dist-info/WHEEL
traceroute-19.2.0.dist-info/top_level.txt
traceroute-19.2.0.dist-info/RECORD
